eg_helpers/__init__.py
eg_helpers/utils_debug.py
eg_helpers/utils_debug_ascii_art.py
eg_helpers/utils_openai.py
eg_helpers/utils_time.py
eg_helpers-0.1.2.dist-info/METADATA
eg_helpers-0.1.2.dist-info/WHEEL
eg_helpers-0.1.2.dist-info/top_level.txt
eg_helpers-0.1.2.dist-info/RECORD
