Metadata-Version: 2.1
Name: eg-helpers
Version: 0.1.2
Summary: Just some helper functions I use in my projects
Home-page: https://github.com/Talla/eg_helpers
Author: Eduard Germis
Author-email: edugermis@gmail.com
License: MIT
Requires-Dist: pandas (>=2.0.1)
Requires-Dist: pytz (>=2023.3)
Requires-Dist: regex (>=2022.10.31)
Requires-Dist: tiktoken (>=0.4.0)
